vega_sim/__init__.py
vega_sim/api/__init__.py
vega_sim/api/data.py
vega_sim/api/data_raw.py
vega_sim/api/faucet.py
vega_sim/api/governance.py
vega_sim/api/helpers.py
vega_sim/api/market.py
vega_sim/api/trading.py
vega_sim/constants.py
vega_sim/devops/README.md
vega_sim/devops/classes.py
vega_sim/devops/example_tokens.json
vega_sim/devops/registry.py
vega_sim/devops/run_agent.py
vega_sim/devops/run_scenario.py
vega_sim/devops/scenario.py
vega_sim/devops/wallet.py
vega_sim/environment/__init__.py
vega_sim/environment/agent.py
vega_sim/environment/environment.py
vega_sim/grpc/__init__.py
vega_sim/grpc/client.py
vega_sim/local_data_cache.py
vega_sim/network_service.py
vega_sim/null_service.py
vega_sim/parameter_test/__init__.py
vega_sim/parameter_test/parameter/__init__.py
vega_sim/parameter_test/parameter/configs.py
vega_sim/parameter_test/parameter/experiment.py
vega_sim/parameter_test/parameter/loggers.py
vega_sim/parameter_test/run.py
vega_sim/proto/__init__.py
vega_sim/proto/blockexplorer/api/v1/blockexplorer_pb2.py
vega_sim/proto/blockexplorer/api/v1/blockexplorer_pb2_grpc.py
vega_sim/proto/data_node/__init__.py
vega_sim/proto/data_node/api/__init__.py
vega_sim/proto/data_node/api/v2/__init__.py
vega_sim/proto/data_node/api/v2/trading_data_pb2.py
vega_sim/proto/data_node/api/v2/trading_data_pb2_grpc.py
vega_sim/proto/vega/__init__.py
vega_sim/proto/vega/api/__init__.py
vega_sim/proto/vega/api/v1/__init__.py
vega_sim/proto/vega/api/v1/core_pb2.py
vega_sim/proto/vega/api/v1/core_pb2_grpc.py
vega_sim/proto/vega/api/v1/corestate_pb2.py
vega_sim/proto/vega/api/v1/corestate_pb2_grpc.py
vega_sim/proto/vega/assets_pb2.py
vega_sim/proto/vega/assets_pb2_grpc.py
vega_sim/proto/vega/chain_events_pb2.py
vega_sim/proto/vega/chain_events_pb2_grpc.py
vega_sim/proto/vega/checkpoint/__init__.py
vega_sim/proto/vega/checkpoint/v1/__init__.py
vega_sim/proto/vega/checkpoint/v1/checkpoint_pb2.py
vega_sim/proto/vega/checkpoint/v1/checkpoint_pb2_grpc.py
vega_sim-1.2.1.dist-info/LICENSE
vega_sim-1.2.1.dist-info/METADATA
vega_sim-1.2.1.dist-info/WHEEL
vega_sim-1.2.1.dist-info/RECORD
